petrirl/__init__.py
petrirl/callbacks/gpumonitor.py
petrirl/callbacks/policysetter.py
petrirl/common/__init__.py
petrirl/common/build_blocks.py
petrirl/common/instance_loader.py
petrirl/common/instances/__init__.py
petrirl/common/instances/BU/bu01
petrirl/common/instances/BU/bu02
petrirl/common/instances/BU/bu03
petrirl/common/instances/BU/bu04
petrirl/common/instances/BU/bu05
petrirl/common/instances/BU/bu06
petrirl/common/instances/BU/bu07
petrirl/common/instances/BU/bu08
petrirl/common/instances/BU/bu09
petrirl/common/instances/BU/bu10
petrirl/common/instances/BU/trans_20_1
petrirl/common/instances/BU/trans_4_1
petrirl/common/instances/BU/trans_4_2
petrirl/common/instances/BU/trans_4_3
petrirl/common/instances/BU/trans_4_4
petrirl/common/instances/Demirkol/cscmax_20_15_1.txt
petrirl/common/instances/Demirkol/cscmax_20_15_10.txt
petrirl/common/instances/Demirkol/cscmax_20_15_5.txt
petrirl/common/instances/Demirkol/cscmax_20_15_7.txt
petrirl/common/instances/Demirkol/cscmax_20_15_8.txt
petrirl/common/instances/Demirkol/cscmax_20_20_2.txt
petrirl/common/instances/Demirkol/cscmax_20_20_3.txt
petrirl/common/instances/Demirkol/cscmax_20_20_4.txt
petrirl/common/instances/Demirkol/cscmax_20_20_6.txt
petrirl/common/instances/Demirkol/cscmax_20_20_9.txt
petrirl/common/instances/Demirkol/cscmax_30_15_10.txt
petrirl/common/instances/Demirkol/cscmax_30_15_2.txt
petrirl/common/instances/Demirkol/cscmax_30_15_5.txt
petrirl/common/instances/Demirkol/cscmax_30_15_6.txt
petrirl/common/instances/Demirkol/cscmax_30_15_9.txt
petrirl/common/instances/Demirkol/cscmax_30_20_3.txt
petrirl/common/instances/Demirkol/cscmax_30_20_4.txt
petrirl/common/instances/Demirkol/cscmax_30_20_6.txt
petrirl/common/instances/Demirkol/cscmax_30_20_7.txt
petrirl/common/instances/Demirkol/cscmax_30_20_9.txt
petrirl/common/instances/Demirkol/cscmax_40_15_3.txt
petrirl/common/instances/Demirkol/cscmax_40_15_4.txt
petrirl/common/instances/Demirkol/cscmax_40_15_6.txt
petrirl-0.2.1.dist-info/METADATA
petrirl-0.2.1.dist-info/WHEEL
petrirl-0.2.1.dist-info/top_level.txt
petrirl-0.2.1.dist-info/RECORD
