Metadata-Version: 2.4
Name: petrirl
Version: 0.2.1
Summary: PetriRL : Advanced Scheduling with Petri Nets and Reinforcement Learning
Home-page: https://www.fh-swf.de/de/forschung___transfer_4/labore_3/labs/labor_fuer_automatisierungstechnik__soest_1/standardseite_57.php
Author: Sofiene Lassoued
Author-email: lassoued.sofiene@fh-swf.de
Project-URL: Repository, https://github.com/Sofiene-Uni/PetriRL-Framework
Requires-Dist: gymnasium
Requires-Dist: pandas
Requires-Dist: numpy
Dynamic: author
Dynamic: author-email
Dynamic: description
Dynamic: description-content-type
Dynamic: home-page
Dynamic: project-url
Dynamic: requires-dist
Dynamic: summary
